gumnut_assembler/__init__.py
gumnut_assembler/assembler.py
gumnut_assembler/exceptions.py
gumnut_assembler-4.0.0.dist-info/LICENSE
gumnut_assembler-4.0.0.dist-info/METADATA
gumnut_assembler-4.0.0.dist-info/WHEEL
gumnut_assembler-4.0.0.dist-info/entry_points.txt
gumnut_assembler-4.0.0.dist-info/top_level.txt
gumnut_assembler-4.0.0.dist-info/RECORD
